{
  "kind": "collectionType",
  "collectionName": "animation_templates",
  "info": {
    "singularName": "animation-template",
    "pluralName": "animation-templates",
    "displayName": "AnimationTemplate"
  },
  "options": {
    "draftAndPublish": true
  },
  "pluginOptions": {},
  "attributes": {
    "name": {
      "type": "string"
    },
    "slug": {
      "type": "uid",
      "targetField": "name"
    },
    "remotionComponent": {
      "type": "string"
    },
    "fps": {
      "type": "integer"
    },
    "duration": {
      "type": "integer"
    },
    "schema": {
      "type": "json"
    },
    "previewCover": {
      "type": "media",
      "multiple": false,
      "allowedTypes": [
        "images",
        "files",
        "videos",
        "audios"
      ]
    },
    "contents": {
      "type": "relation",
      "relation": "oneToMany",
      "target": "api::animation-content.animation-content",
      "mappedBy": "template"
    }
  }
}
